{
    "tags": {
        "allowUnknownTags": true
    },
    "source": {
        "include": ["./src"],
        "includePattern": ".+\\.js(doc|x)?$",
        "excludePattern": "(^|\\/|\\\\)_",
        "exclude": ["./src/index.js"]
    },
    "plugins": [],
    "opts": {
        "encoding": "utf8",
        "destination": "./doc/doc-page/",
        "recurse": true
    },
    "templates": {
        "cleverLinks": false,
        "monospaceLinks": false,
        "default": {
            "outputSourceFiles": true
        }
    }
}